setup.py
openProductionHW/__init__.py
openProductionHW.egg-info/PKG-INFO
openProductionHW.egg-info/SOURCES.txt
openProductionHW.egg-info/dependency_links.txt
openProductionHW.egg-info/not-zip-safe
openProductionHW.egg-info/requires.txt
openProductionHW.egg-info/top_level.txt
openProductionHW/BP730/BP730.py
openProductionHW/BP730/__init__.py
openProductionHW/CV2Cam/CV2Cam.py
openProductionHW/CV2Cam/__init__.py
openProductionHW/DPS/DPS.py
openProductionHW/DPS/__init__.py
openProductionHW/KernPCB/KernPCB.py
openProductionHW/KernPCB/__init__.py
openProductionHW/LPM01/LPM01.py
openProductionHW/LPM01/__init__.py
openProductionHW/M2D2/M2D2.py
openProductionHW/M2D2/M2D2Bepp.py
openProductionHW/M2D2/__init__.py
openProductionHW/NI6001/NI6001.py
openProductionHW/NI6001/__init__.py
openProductionHW/TIFlashProgrammer/TIProgrammer.py
openProductionHW/TIFlashProgrammer/__init__.py