Metadata-Version: 1.0
Name: openProductionHW
Version: 0.0.3
Summary: Library to interface HW within openProduction
Home-page: https://github.com/Coimbra1984/openProductionHW
Author: Markus Proeller
Author-email: markus.proeller@pieye.org
License: GPLv3
Platform: UNKNOWN
